Workbook

Sheet Contrato
G2: CONTRATO DE MATRÍCULA
G3: GESTIÓN ADMINISTRATIVA Y FINANCIERA
G5: Código: GOT-DOC-01 | J5: Versión:03 | M5: Vigencia: 31/12/21 | Q5: Página: 1 de 4
B7: FOTOGRAFÍA 3 x 4 | F7: Unicab Corporación Educativa "Colegio UNICAB Virtual" | R7: FECHA
F8: EDUCACIÓN BÁSICA PRIMARIA, BÁSICA SECUNDARIA Y MEDIA ACADÉMICA | R8: Día | S8: Mes | T8: Año
F9: Resolución 061 de 15 de Diciembre de 2007 S.E. y Cultura de Sogamoso
F10: Resolución 0155 de 21 de julio de 2010 - Resolución 326 de 22 de septiembre de 2015
F12: VALOR MATRÍCULA | L12: ANUAL PENSIÓN
F13: ESTADO DE | G13: ESTUDIANTE NUEVO | J13: HOMOLOGACIÓN | M13: CONVALIDACIÓN | R13: RENOVACIÓN
F14: MATRÍCULA | G14: UNIDAD A LA QUE INGRESA | J14: PRIMARIA | M14: SECUNDARIA | R14: M. ACADÉMICA
F15: GRADO AL QUE INGRESA | M15: CICLO DE INGRESO
F16: TIPO DE | G16: CONTADO | H16: ACUERDO | J16: CONVENIO | R16: No. CONTRATO - FICHA
F17: MATRÍCULA
B19: NOMBRE DEL
B20: ESTUDIANTE
B21: DOCUMENTO | C21: T.I | D21: C.C | E21: C.E | F21: NÚMERO DE DOCUMENTO | I21: LUGAR Y FECHA DE NACIMIENTO | O21: Día | P21: Mes | R21: Año | T21: SEXO
B22: DE IDENTIDAD
B23: DIRECCIÓN | K23: CIUDAD/DEPTO.
B24: ÚLTIMO | O24: ÚLTIMO GRADO
B25: COLEGIO | O25: APROBADO
B26: ESTADO CIVIL | J26: EDAD | O26: ESTRATO
B27: TELÉFONOS | K27: EMAIL
B28: CONDICIÓN | K28: TIEMPO QUE DEDICA
B29: SOCIOECONÓMICA
B30: ACREDITADA
B31: DISCAPACIDAD | C31: NINGUNA | F31: FÍSICA | G31: COGNITIVA | H31: AUDITIVA | J31: VISUAL | K31: MENTAL | M31: OTRA | N31: DE EXISTIR, POR FAVOR ESPECIFIQUE CUÁL ES LA INCAPAIDAD
B34: NOMBRE DEL
B35: Acudiente
B36: DOCUMENTO | I36: DIRECCIÓN DE RESIDENCIA | Q36: TELÉFONOS
B37: DE IDENTIDAD | C37: EXPEDIDA EN.
B38: PROFESIÓN | J38: EMPRESA
B39: TELÉFONO | J39: EMAIL
B41: NOMBRE DEL
B42: PADRE
B43: DOCUMENTO | I43: DIRECCIÓN DE RESIDENCIA | Q43: TELÉFONOS
B44: DE IDENTIDAD | C44: EXPEDIDA EN.
B45: PROFESIÓN | J45: EMPRESA
B46: TELÉFONO | J46: EMAIL
B48: NOMBRE DE
B49: LA MADRE
B50: DOCUMENTO | I50: DIRECCIÓN DE RESIDENCIA | Q50: TELÉFONOS
B51: DE IDENTIDAD | C51: EXPEDIDA EN.
B52: PROFESIÓN | J52: EMPRESA
B53: TELÉFONO | J53: EMAIL
B55: MEDIOS DE PAGO | C55: BANCO AV VILLAS | K55: CAJA SOCIAL DE AHORRO
C56: CUENTA CORRIENTE No. 720 - 17457 - 2 | K56: CUENTA CORRIENTE No. 21003786216
C57: TITULAR: UNICAB CORPORACIÓN EDUCATIVA | K57: TITULAR: UNICAB CORPORACIÓN EDUCATIVA
B58: REFERENCIA | C58: NÚMERO DE CÉDULA DE CIUDADANÍA DEL PADRE DE | J58: REFERENCIA | K58: NÚMERO DE CÉDULA DE CIUDADANÍA DEL PADRE DE
C59: FAMILIA O Acudiente | K59: FAMILIA O Acudiente
G66: CONTRATO DE MATRÍCULA
G67: GESTIÓN ADMINISTRATIVA Y FINANCIERA
G69: Código: GOT-DOC-01 | J69: Versión:03 | M69: Vigencia: 31/12/21 | Q69: Página: 2 de 4
A71: ACTA DE COMPROMISO INSTITUCIONAL
B73: En ejercicio del derecho constitucional consagrado en el inciso 4º del artículo 68 constitucional que indica que “Los padres de familia tendrán derecho a escoger el tipo de educación para sus
B74: hijos menores.” y con el propósito de garantizar el ejercicio de los derechos fundamentales de los niños, niñas y adolescentes consagrados en los artículos 26, 27, 44, 67, 68 y 70 de la
B75: Constitución Política de Colombia, y en particular de en su condición de | N75: postulante admitido , quien en adelante se denominará
B76: BENEFICARIO-ESTUDIANTE, los señores | K76: y | T76: Padre (s) o
B77: Acudiente (s) y representante legal del BENEFICIARIO-ESTUDIANTE de una parte, y de otra parte, IMELDA VERGARA GÓMEZ, identificada como aparece al pie de mi firma como representante
B78: legal de la UNICAB Corporación Educativa y rectora del Colegio UNICAB Virtual, quien en adelante se denominará la INSTITUCIÓN, institución de carácter privada, hemos acordado suscribir
B79: el presente CONTRATO DE MATRÍCULA por un año académico, el cual se regirá por las normas contenidas en el manual de convivencia y en especial por las siguientes cláusulas:
B81: PRIMERA. OBJETO: El presente contrato tiene por objeto la prestación de servicios educativos con metodología virtual al BENEFICIARIO-ESTUDIANTE, con el fin de lograr su formación
B82: personal, cultural y social fundada en una concepción integral de la persona humana, de su dignidad, de sus derechos y deberes, teniendo en cuenta los fines de la educación previstos en
B83: la ley 115 de 1994 y demás leyes, decretos y normas concordantes, vigentes a la fecha de la firma del presente documento, con obligaciones de los educadores, educandos y los padres de
B84: familia. Las obligaciones que se adquieren en el presente contrato son correlativas y esenciales para la obtención del objeto común.
B86: SEGUNDA. OBLIGACIONES DE LOS PADRES- AcudienteS- REPRESENTANTES LEGALES: Son obligaciones de los padres- Acudientes- representantes legales, además de las
B87: previstas en la Constitución Política Colombiana y la normatividad vigente en materia de potestad parental, guardas y representación legal de menores de edad: 1) Matricular al
B88: BENFICIARIO-ESTUDIANTE en las fechas establecidas por la INSTITUCIÓN; 2) Participar en la integración de los órganos de gobierno escolar y demás consejos y comités que
B89: contribuyan a lograr la participación de los padres- Acudientes- representantes legales en el proceso pedagógico ECOSISTEMA UNICAB VIRTUAL, en la forma prevista en las normas
B90: vigentes y el manual de convivencia. 3) Participar libremente en las reuniones de Padres de Familia; 4) Informarse sobre el rendimiento académico y comportamiento del Estudiante y
... B106: los Padres estén a Paz y Salvo con el Colegio.
B108: QUINTA- DURACIÓN: Este contrato tiene vigencia de un (1) año lectivo escolar, a partir del día | L108: de | O108: de | R108: al día | T108: de
C109: de
B111: SEXTA. COSTOS: Los padres- Acudientes- representantes legales se comprometen al pago puntual de la matrícula anual, pensión mensual, derechos de grado y demás costos educativos.
B112: El pago de los costos se hará únicamente a través de los diferentes medios de pago autorizados por la institución y en los tiempos señalados por esta.
B114: El valor anual corresponde a la suma de | P114: $( | U114: )
B115: que para efecto de la pensión se pagará en | H115: cuotas fijas mensuales anticipadas de | R115: $( | U115: )
B116: cada una.
B118: Los padres- Acudientes- representantes legales firmarán un pagaré o título que preste mérito ejecutivo en iguales condiciones con la respectiva carta de instrucciones, de acuerdo con el
B119: cual, el mismo, se diligenciará con el valor en mora en que los padres- Acudientes- representantes legales se encuentren con la Institución por concepto de matrícula, mensualidades de
B120: pensión y las demás obligaciones que se generen en virtud del presente contrato y del PEI. Igualmente pagarán los gastos de cobranza judicial y extrajudicial, honorarios de abogado y
B121: demás gastos que la INSTITUCIÓN haya cancelado derivados de cualquier clase de obligaciones directas o indirectas de los padres- Acudientes- representantes legales y hasta su
B122: cancelación total, sin perjuicio de las acciones legales que el tenedor del presente título tenga para obtener el pago de la indemnización total por los perjuicios que por su incumplimiento,
B123: acción u omisión, se le hayan ocasionado.
B125: Parágrafo Primero. La primera cuota se cancelará dentro de los DIEZ (10) primeros días calendario del mes, independiente de la fecha de ingreso, y las restantes en los meses
B126: subsiguientes para un total de | G126: pagos anuales hasta la finalización del año académico.
B128: Parágrafo Segundo. La ausencia temporal o total dentro del mes por enfermedad u otra causal atribuible al Estudiante- Beneficiario, padres- Acudientes- representantes legales, así sea
B129: por causa fortuita o fuerza mayor, no dará derecho al aquí comprometido a descontar suma alguna de lo obligado a pagar o que el colegio le haga devoluciones o abonos a meses
B130: posteriores.
G133: CONTRATO DE MATRÍCULA
G134: GESTIÓN ADMINISTRATIVA Y FINANCIERA
G136: Código: GOT-DOC-01 | J136: Versión:03 | M136: Vigencia: 31/12/21 | Q136: Página: 3 de 4
B138: Parágrafo Tercero. En caso de retiro voluntario del estudiante después de iniciado el año escolar, no habrá lugar a devoluciones por concepto de matrícula, en caso de retiro antes de
B139: iniciarse el año escolar se devolverá lo equivalente al 70% por concepto de matrícula ya que el restante 30% se tomará por gastos administrativos a favor de la INSTITUCIÓN. En caso que
B140: el retiro se efectúe después que el estudiante ingresó a plataforma no habrá lugar a devolución y los padres de familia o Acudientes deberán informar por escrito su decisión con (quince)
B141: 15 días de anticipación, de lo contrario se hará efectivo el cobro total de la pensión.
B143: Parágrafo Cuarto. Expresamente los padres- Acudientes- representantes legales, autorizan a la Institución o al acreedor que hiciere sus veces, para dar por terminado el plazo pactado y/o
B144: exigir de inmediato, judicial o extrajudicialmente, el pago total del valor de las obligaciones pendientes, gastos de cobranza y demás obligaciones accesorias, cuando exista una obligación
B145: incumplida o en mora a cargo de los padres- Acudientes- representantes legales y en los casos previstos en el pagaré y demás documentos suscritos por los padres- Acudientes-
B146: representantes legales, así como, en los siguientes eventos sin necesidad de requerimiento privado o judicial, sin consideración del vencimiento de plazos pactados a los cuales renuncian
B147: los padres- Acudientes- representantes legales de manera expresa en razón del claro conocimiento de los términos convenidos de las obligaciones de los padres- Acudientes-
...

Sheet Pagare
G2: CONTRATO DE MATRÍCULA
G3: GESTIÓN ADMINISTRATIVA Y FINANCIERA
G5: Código: GOT-DOC-01 | J5: Versión:03 | M5: Vigencia: 31/12/21 | Q5: Página: 1 de 2
C7: DATOS IDENTIFICADORES DEL PAGARÉ | R7: FECHA SUSCRIPCIÓN
C8: POR CONTRATO DE MATRÍCULA Y PENSIÓN | R8: Día | S8: Mes | T8: Año
G9: PAGARÉ No. | J9: =+Contrato!R17 -> 0 | R9: =+Contrato!R9 -> 0 | S9: =+Contrato!S9 -> 0 | T9: =+Contrato!T9 -> 0
B11: No. CONTRATO | D11: =+Contrato!R17 -> 0 | H11: FECHA CONTRARO | K11: =CONCATENATE(Contrato!T9,"/",Contrato!S9,"/",Contrato!R9) -> // | O11: VALOR TOTAL
B12: VALOR EN LETRAS
B13: DESCRIMINACIÓN | D13: CONCEPTO MATRÍCULA | H13: OTROS COSTOS | K13: VALOR PENSIÓN | P13: NO. MENSUALIDADES
B14: DEL PAGO
B16: NOMBRE DEL | C16: =+Contrato!C34 -> 0
B17: DEUDOR
B18: DOCUMENTO | C18: =+Contrato!C36 -> 0 | I18: DIRECCIÓN DE RESIDENCIA | Q18: TELÉFONOS
B19: DE IDENTIDAD | C19: EXPEDIDA EN. | F19: =IF(Contrato!F37="","",Contrato!F37) | I19: =IF(Contrato!I37="","",Contrato!I37) | Q19: =IF(Contrato!Q37="","",Contrato!Q37)
B20: PROFESIÓN | C20: =IF(Contrato!C38="","",Contrato!C38) | J20: EMPRESA | K20: =IF(Contrato!K38="","",Contrato!K38)
B21: TELÉFONO | C21: =IF(Contrato!C39="","",Contrato!C39) | J21: EMAIL | K21: =IF(Contrato!K39="","",Contrato!K39)
B22: ESTUDIANTE | C22: =IF(Contrato!C19="","",Contrato!C19) | J22: DOCUMENTO | K22: =IF(Contrato!F22="","",Contrato!F22) | Q22: GRADO | S22: =IF(Contrato!H15="","",Contrato!H15)
B24: DATOS DEL | C24: Unidad de Capacitación Empresarial de Boyacá "UNICAB Corporación Educativa" administradora colegio UNICAB virtual | P24: NIT | R24: 826.002.762-1
B25: ACREEDOR
B26: REPRESENTANTE | C26: IMELDA VERGARA GÓMEZ | K26: CÉDULA | O26: 46.352.777 de Sogamoso
B27: TELÉFONO | C27: 318 714 3774 | J27: E- MAIL | K27: cartera@unicab.org
A29: CARTA DE INSTRUCCIONES
B31: Por medio el presente, el denominado DEUDOR, descrito en los datos identificadores del presente documento, manifiesto mi voluntad libre y espontánea de suscribir el
B32: presente Pagaré que garantiza el pago de la matricula, pensiones y otros costos académicos correspondientes al servicio educativo del año lectivo de | T32: =+Contrato!P108 -> 0 | V32: ,
B33: contratado con el Colegio UNICAB Virtual.
B35: Por consiguiente, en calidad de acudiente / padre de familia, declaro que soy mayor de edad, me identifico como aparece al pie de mi firma, que obro en nombre propio
B36: como representante y/o benefactor del estudiante de la referencia, manifiesto que gozo de capacidad legal para celebrar este contrato y suscribir este título valor, que
B37: establece de manera clara, expresa y por consiguiente exigible que debo y pagaré, incondicional y solidariamente a la orden del ACREEDOR de la referencia o a la
B38: persona natural o jurídica a quien el mencionado acreedor ceda o endose sus derechos sobre este pagaré, la suma cierta en moneda legal colombiana y además:
B40: PRIMERO. OBJETO: Que en virtud del presente título valor EL DEUDOR se compromete a pagar incondicionalmente a la orden del ACREEDOR, la suma estipulada,
B41: que dicho valor corresponde al valor total de la matricula, los cánones de pensión y la suma referida como otros costos por concepto de la prestación del servicio
B42: educativo del beneficiario, descrito en el cuadro de la referencia, que el domicilio contractual del presente pagaré es la ciudad de Sogamoso Boyacá, país Colombia.
B44: SEGUNDO: FORMAS DE PAGO. Que la suma expresada, será cancela en un pago inicial por concepto de matrícula, un pago posterior por concepto de costos
B45: académicos y | C45: =+Contrato!F126 -> 0 | F45: pagos mensuales correspondientes al concepto de pensión, durante los diez (10) primeros días de cada mes, comenzando desde el
B46: =CONCATENATE(Contrato!K108," de ",Contrato!M108," de ",Contrato!P108) -> de de | F46: terminando en el año académico, en los canales de pago establecidos por el colegio. Los pagos atrasados y sus respectivos intereses
B47: podrán hacerse en el Banco Caja Social al número de cuenta Corriente No. 21003786216 Titular UNICAB Corporación Educativa en formato de consignación
B48: Comprobante Universal de Recaudo, o en las oficinas del colegio ubicadas en Calle 13ª 16 - 60 Sogamoso (Boyacá); en BANCO AV VILLAS CUENTA CORRIENTE No.
B49: 72017457–2 TITULAR: UNICAB CORPORACIÓN EDUCATIVA, y por los canales de pago en línea Epayco según instructivo en la página
B50: https://unicab.org/pagos_payservices.php
B52: TERCERO: INTERÉS POR MORA. En caso de mora reconoceré intereses en favor del ACREEDOR el porcentaje establecido al máximo legal bancario vigente a la mas
B53: alta tasa permitida por la Ley, desde el día siguiente a la fecha de exigibilidad del presente pagare, y hasta cuando el pago se normalice o el pago total se efectúe.
B55: CUARTO: CLÁUSULA ACLARATORIA. EL Colegio UNICAB Virtual o a quien este designe podrá dar por extinguido el plazo y exigir el pago inmediato de la totalidad
B56: del capital judicial o extrajudicialmente cuando: (a) el deudor incumpla cualquiera de las obligaciones derivadas del presente documento, (b) se incumpla con el
B57: contrato de matrícula, (c) por orden sustentada del Consejo Directivo en sanción.
B59: QUINTO. CESIÓN: Acepto desde ahora la cesión que de este pagare hiciera Colegio UNICAB Virtual a cualquier persona natural o jurídica con el fin de hacerlo efectivo,
B60: quien expresamente declara excusado el protesto del presente pagaré y los requerimientos judiciales o extrajudiciales para la constitución en mora.
G66: CONTRATO DE MATRÍCULA
G67: GESTIÓN ADMINISTRATIVA Y FINANCIERA
G69: Código: GOT-DOC-01 | J69: Versión:03 | M69: Vigencia: 31/12/21 | Q69: Página: 2 de 2
B71: SEXTO: COSTAS POR EXIGIBILIDAD. Expresamente declaro excusado el protesto del presente pagaré y los requerimientos judiciales o extrajudiciales para la
B72: constitución en mora. En caso de que haya lugar al recaudo judicial o extrajudicial de la obligación contenida en el presente título valor será a mi cargo las costas
B73: judiciales y/o los honorarios que se causen por tal razón serán de mi cargo los pagos por costas de la cobranza judicial si hubiera lugar a ella.
B75: Parágrafo al artículo SEGUNDO: OBLIGACIONES DE LOS PADRES, numeral 7. El cumplimiento extemporáneo de la obligación contenida en el numeral 7° de la
B76: cláusula seguna del presente contrato generará la aplicación y pago de un recargo equivalente al 5% del costo de la pensión insoluta, el cual, se aplicará sin perjuicio
B77: de la generación de intereses moratorios y/o indexación.
B80: AL FIRMAR EL PRESENTE PAGARÉ EN BLANCO, EL DEUDOR QUEDA COMPROMETIDO EN SU TOTALIDAD AL | L80: HUELLA
B81: CLAUSULADO DE LA PARTE INICIAL DEL CONTRATO DE MATRICULA DE LA REFERENCIA, CON LOS
B82: RESPECTIVOS REAJUSTES ECONÓMICOS QUE SE FIJEN PARA LA TEMPORADA ACADÉMICA VIGENTE Y LOS
B83: DIFERENTES CAMBIOS REGLAMENTARIOS Y NORMATIVOS QUE SE PRESENTEN A LA FECHA DE SUSCRIPCIÓN
B84: DEL PRESENTE DOCUMENTO.
B86: ACEPTANTE: | C86: =+Contrato!C235 -> 0
B87: DOCUMENTO: | C87: =+Contrato!C236 -> 0 | G87: DE | H87: =IF(Contrato!H236="","",Contrato!H236) | P87: FIRMA DEL DEUDOR

Sheet Colores
A1: 42 86 138 | B1: #2A568A | Z1: F
Z2: M
A3: 74 135 209 | B3: #4A87D1
A5: 219 228 240 | B5: #DBE4F0
A7: 182 221 232 | B7: #B6DDE8
A9: 217 217 217 | B9: #D9D9D9
